ec2instances/info/__init__.py
ec2instances.info-0.0.2.dist-info/DESCRIPTION.rst
ec2instances.info-0.0.2.dist-info/METADATA
ec2instances.info-0.0.2.dist-info/RECORD
ec2instances.info-0.0.2.dist-info/WHEEL
ec2instances.info-0.0.2.dist-info/metadata.json
ec2instances.info-0.0.2.dist-info/top_level.txt
