Metadata-Version: 2.0
Name: ec2instances.info
Version: 0.0.2
Summary: The community-maintained dataset of ec2 instance types and pricing
Home-page: https://github.com/powdahound/ec2instances.info
Author: Garret Heaton
Author-email: github@garretheaton.com
License: MIT
Platform: UNKNOWN
